{
  "tasks": [
    {
      "id": 1,
      "text": "Terminar primero modulo de angular",
      "day": "Agosto 5 a las 12:00",
      "reminder": true
    },
    {
      "id": 3,
      "text": "Investigar sobre bootstrap",
      "day": "Agosto 5 a las 19:00",
      "reminder": false
    },
    {
      "id": 4,
      "text": "Leer mi libros",
      "day": "Agosto 5 a las 21:00",
      "reminder": false
    },
    {
      "text": "leer angular",
      "day": "Maniana",
      "reminder": true,
      "id": 5
    }
  ]
}